pyqt_slideshow/__init__.py
pyqt_slideshow/slideShow.py
pyqt_slideshow/ico/__init__.py
pyqt_slideshow/ico/next.svg
pyqt_slideshow/ico/prev.svg
pyqt_slideshow/widgets/__init__.py
pyqt_slideshow/widgets/aniButton.py
pyqt_slideshow/widgets/graphicsView.py
pyqt_slideshow/widgets/svgButton.py
pyqt_slideshow-0.0.22.dist-info/LICENSE
pyqt_slideshow-0.0.22.dist-info/METADATA
pyqt_slideshow-0.0.22.dist-info/WHEEL
pyqt_slideshow-0.0.22.dist-info/top_level.txt
pyqt_slideshow-0.0.22.dist-info/RECORD
