Metadata-Version: 2.1
Name: pyqt-slideshow
Version: 0.0.22
Summary: PyQt widget for slide show
Home-page: https://github.com/yjg30737/pyqt-slideshow.git
Author: Jung Gyu Yoon
Author-email: yjg30737@gmail.com
License: MIT
License-File: LICENSE
